monzy/__init__.py
monzy/get_balances.py
monzy/get_transactions.py
monzy/upload_balances.py
monzy/upload_transactions.py
monzy/utils/__init__.py
monzy/utils/custom_logger.py
monzy/utils/date_utils.py
monzy/utils/db.py
monzy/utils/sql_templates.py
monzy-0.1.0.dist-info/METADATA
monzy-0.1.0.dist-info/WHEEL
monzy-0.1.0.dist-info/RECORD
