Metadata-Version: 2.1
Name: monzy
Version: 0.1.0
Summary: Package to interact with Monzo API to fetch transactions and upload to a database
Author: Elias Benaddou Idrissi
Author-email: e.benaddou@hotmail.com
Requires-Python: >=3.11,<4.0
Classifier: Programming Language :: Python :: 3
Classifier: Programming Language :: Python :: 3.11
Classifier: Programming Language :: Python :: 3.12
Requires-Dist: loguru (==0.7.2)
Requires-Dist: monzo-api (==1.1.0)
Requires-Dist: pandas (>=2.2.2,<3.0.0)
Requires-Dist: sqlalchemy (>=2.0.31,<3.0.0)
